LICENSE
MANIFEST.in
README.md
setup.cfg
setup.py
mezzanine_modal_announcements.egg-info/PKG-INFO
mezzanine_modal_announcements.egg-info/SOURCES.txt
mezzanine_modal_announcements.egg-info/dependency_links.txt
mezzanine_modal_announcements.egg-info/top_level.txt
modal_announcements/.DS_Store
modal_announcements/__init__.py
modal_announcements/admin.py
modal_announcements/defaults.py
modal_announcements/models.py
modal_announcements/tests.py
modal_announcements/views.py
modal_announcements/migrations/.DS_Store
modal_announcements/migrations/0001_initial.py
modal_announcements/migrations/__init__.py
modal_announcements/templates/includes/announcements.html
modal_announcements/templatetags/__init__.py
modal_announcements/templatetags/announcement_tags.py