Metadata-Version: 1.1
Name: mezzanine-modal-announcements
Version: 1.1.3
Summary: Popup announcements for Mezzanine websites utilizing Bootstrap modals.
Home-page: https://github.com/joshcartme/mezzanine-modal-announcements
Author: Joshua Cartmell
Author-email: chat@joshc.io
License: UNKNOWN
Download-URL: https://github.com/joshcartme/mezzanine-modal-announcements/tarball/1.1.3
Keywords: mezzanine,django,announcements
Platform: UNKNOWN
